{"paths":{},"types":[],"uuids":["29FYIk+N1GYaeWH/q1NxQO","e97GVMl6JHh5Ml5qEDdSGa","f0BIwQ8D5Ml7nTNQbh1YlS","01eOQGuPZJRp0QBZL/CCDr","05sHHebvBMDqUyaLKmI+Q4","07xsnEZy5KBKjATRCNvxJR","0c6ftrYV9Jg5pIn0BdPeA7","0eFiCenTZKVKftzMwVvZvP","1e3baddbNOLq9E/q17JGTc","3aLL5L2lpKZJPNFMuDYaov","3dua0zIeNGDpEdakEenScM","3eg2oVTgpAZ4IIzRb/uuQ6","4fBy4aXCtJe6jjUwVKhLsJ","62haIqmHpEOI9AiNSbTxd2","63wdLHOqBFbYyicEi4Lr9H","71VhFCTINJM6/Ky3oX9nBT","72NYujEjVLYYEqYuB57H6D","7edvsT/AFM9pVtVw8PdvDM","8fO7VGJpFB/bgHa1ej6KZv","92a9ixJttJ34ElPnjtMeJE","b4P/PCArtIdIH38t6mlw8Y","bczWMv2K5B24XoBPEXPkD0","c5InwrEFpGD6MgmzeuENwH","c6mlks14xD/q9jM736qcO2","d6DqzP/FlDGYZ6bBTfF9LE","e1j30B8AVORYofQGcCvsc6","e2RXRsbnFCqJeRXEZIkDI5","e4rTZCvmVGMJhpzuaFWcM3","e8Ueib+qJEhL6mXAHdnwbi","ebVr9IHrBLNqQGUmWV0MRQ","f09OwQtK5CSrvTAfu4jS6S","f1LBFXERFKw4ir7LJv1H57","f7c2GK4YtMTLn0j+96FvFQ","02delMVqdBD70a/HSD99FK","05l7MyH3pENpc1d7jRdiHj","38G8tkUx1P9pFs8p8eYti3","844Q2Dr7FP8qCCtxiMYSbg","93N7GkzRpItrsZpJ7TPSdb","a2MjXRFdtLlYQ5ouAFv/+R","b5cbkiEgRJaag2UYe+Mnm4","bfN1hnA7lGi6uSUm7MXDTQ","cclEsVPu5FnqfBLZZS1K60","d8JxY1HY9HprMTbS7zzMqN","eblX3/UpNB0JD6unDQMNKf","ecpdLyjvZBwrvm+cedCcQy"],"scenes":{"db://assets/scenes/Game.fire":32,"db://assets/scenes/Introduction.fire":16,"db://assets/scenes/Main.fire":10},"redirect":[33,0,44,0],"deps":["internal"],"packs":{"01d0c3060":[4,0,10,13,18,37,21,1,29,2],"04a764700":[34,6,7,0,35,11,14,36,18,38,39,21,40,41,24,42,26,1,43,2,32],"074028da1":[4,0,13,16,1,29,2],"09f8e4536":[3,5,8,9,12,15,17,19,20,22,23,25,27,28,31]},"name":"main","importBase":"import","nativeBase":"native","debug":false,"isZip":false,"encrypted":false,"versions":{"import":["01d0c3060","545e1","04a764700","6ec72","074028da1","7ee97","09f8e4536","14eae",30,"c463d"],"native":[3,"d26e8",5,"0d341",6,"df2bb",7,"b05dd",8,"349ba",9,"3cbcc",11,"14851",12,"df807",14,"289fe",15,"c06a9",17,"c076a",19,"286af",20,"83fcc",22,"feba6",23,"6f469",24,"6a3b6",25,"46df9",26,"a4f4e",27,"ca186",28,"90cf4",30,"481c4",31,"159ec"]}}